aio/run/checker/__init__.py
aio/run/checker/abstract.py
aio/run/checker/checker.py
aio/run/checker/decorators.py
aio/run/checker/interface.py
aio/run/checker/py.typed
aio.run.checker-0.5.8.dist-info/METADATA
aio.run.checker-0.5.8.dist-info/WHEEL
aio.run.checker-0.5.8.dist-info/namespace_packages.txt
aio.run.checker-0.5.8.dist-info/top_level.txt
aio.run.checker-0.5.8.dist-info/RECORD
