Metadata-Version: 2.1
Name: aio.run.checker
Version: 0.5.8
Summary: "Async checker definitions"
Home-page: https://github.com/envoyproxy/toolshed/tree/main/aio.run.checker
Author: Ryan Northey
Author-email: ryan@synca.io
Maintainer: Ryan Northey
Maintainer-email: ryan@synca.io
License: Apache Software License 2.0
Requires-Python: >=3.10.0
Requires-Dist: aio.run.runner (>=0.3.4)
